ab/hf/uploader.py
nn_hf-0.0.0.dist-info/licenses/LICENSE
uploader/_internal/certifi/py.typed
nn_hf-0.0.0.dist-info/METADATA
nn_hf-0.0.0.dist-info/WHEEL
nn_hf-0.0.0.dist-info/top_level.txt
nn_hf-0.0.0.dist-info/RECORD
