Metadata-Version: 2.4
Name: nn-hf
Version: 0.0.0
Summary: Uploader of Deep Model Weights to Hugging Face
Author-email: ABrain One and contributors <AI@ABrain.one>
License: MIT License
Project-URL: Homepage, https://ABrain.one
Project-URL: Repository, https://github.com/ABrain-One/nn-hf
Project-URL: Bug Tracker, https://github.com/ABrain-One/nn-hf/issues
Keywords: hugging face uploader,deep learning model upload,machine learning model sharing,python model uploader,model repository tool,neural network weights upload,AI model deployment tool,hugging face hub integration,command-line model uploader
Classifier: Programming Language :: Python :: 3
Classifier: License :: OSI Approved :: MIT License
Classifier: Operating System :: OS Independent
Classifier: Topic :: Scientific/Engineering :: Artificial Intelligence
Classifier: Topic :: Software Development :: Libraries
Classifier: Intended Audience :: Developers
Classifier: Intended Audience :: Science/Research
Requires-Python: >=3.10
License-File: LICENSE
Requires-Dist: huggingface_hub~=0.29.3
Dynamic: license-file
